pyhoo/__init__.py
pyhoo/config.py
pyhoo/data/fundamentals_type_options.txt
pyhoo/errors.py
pyhoo/getter.py
pyhoo/models/__init__.py
pyhoo/models/abc.py
pyhoo/models/chart.py
pyhoo/models/fundamentals.py
pyhoo/models/iterables.py
pyhoo/models/options.py
pyhoo/parsers/__init__.py
pyhoo/parsers/abc.py
pyhoo/parsers/chart.py
pyhoo/parsers/fundamentals.py
pyhoo/parsers/options.py
pyhoo/requester.py
pyhoo/types/__init__.py
pyhoo/types/chart.py
pyhoo/types/fundamentals.py
pyhoo/types/options.py
pyhoo-0.1.3.dist-info/WHEEL
pyhoo-0.1.3.dist-info/METADATA
pyhoo-0.1.3.dist-info/RECORD
