Metadata-Version: 2.1
Name: pyhoo
Version: 0.1.3
Summary: Yet another unofficial Yahoo Finance API, but with concurrent requests
License: MIT
Keywords: yahoo,finance,api
Author: ROUHARD Pierre
Author-email: pierrerouhard@gmail.com
Requires-Python: >=3.8,<4.0
Classifier: License :: OSI Approved :: MIT License
Classifier: Programming Language :: Python :: 3
Classifier: Programming Language :: Python :: 3.8
Classifier: Programming Language :: Python :: 3.9
Requires-Dist: aiohttp (>=3.6.1,<4.0.0)
Requires-Dist: pandas (>=1.0.0,<2.0.0)
